nonebot_plugin_water_geoup_stats/__init__.py
nonebot_plugin_water_geoup_stats-0.1.1.dist-info/METADATA
nonebot_plugin_water_geoup_stats-0.1.1.dist-info/WHEEL
nonebot_plugin_water_geoup_stats-0.1.1.dist-info/top_level.txt
nonebot_plugin_water_geoup_stats-0.1.1.dist-info/RECORD
