Metadata-Version: 2.1
Name: nonebot-plugin-water-geoup-stats
Version: 0.1.1
Summary: Default template for PDM package
Author-email: zhongwen-4 <2401128923@qq.com>
License: MIT
Requires-Python: >=3.10
Requires-Dist: nonebot2>=2.4.0
Requires-Dist: nonebot-plugin-localstore>=0.7.2
Requires-Dist: nonebot-plugin-apscheduler>=0.5.0
Requires-Dist: aiosqlite>=0.20.0
Requires-Dist: nonebot-adapter-onebot>=2.4.6
